{"name":"Chronos Collapse - La Campanella","illustration":"https://zh.moegirl.org.cn/Special:FilePath/Chronos_Collapse_-_La_Campanella_jacket.png","charts":[{"level":"EZ","difficulty1":2,"difficulty2":2.8,"notes":350,"charter":"Pcat『Scatter』"},{"level":"HD","difficulty1":10,"difficulty2":10.6,"notes":773,"charter":"阿爽『Destroy』"},{"level":"IN","difficulty1":15,"difficulty2":15.9,"notes":1500,"charter":"NerSAN vs. 阿爽『Collapse』"}],"chapter":{"subtitle":"Chapter 7","title":"时钟链接"},"composer":"SunsetRay","bpm":"180","illustrator":"老张","length":"2:33"}